{"blocks":[{"x":510,"y":460,"text":"ход 2 игрока\n(+ожидание)","width":100,"height":40,"type":"Блок","isMenuBlock":false,"fontSize":14,"textHeight":14,"isBold":false,"isItalic":false},{"x":510,"y":370,"text":"ход 1 игрока\n(+ожидание)","width":100,"height":60,"type":"Блок","isMenuBlock":false,"fontSize":14,"textHeight":14,"isBold":false,"isItalic":false},{"x":510,"y":180,"text":"подключение","width":100,"height":40,"type":"Блок","isMenuBlock":false,"fontSize":14,"textHeight":14,"isBold":false,"isItalic":false},{"x":510,"y":260,"text":"расстановка\nна случайные\nпозиции","width":100,"height":60,"type":"Блок","isMenuBlock":false,"fontSize":14,"textHeight":14,"isBold":false,"isItalic":false},{"x":510,"y":580,"text":"ход\nкомпьютера\nв случайном\nнаправлении\n(+ожидание)","width":100,"height":80,"type":"Блок","isMenuBlock":false,"fontSize":14,"textHeight":14,"isBold":false,"isItalic":false},{"x":780,"y":530,"text":"классы\nприбавляются\nв цикле +8 до\nконца поля ||\nпересечения","width":100,"height":80,"type":"Блок","isMenuBlock":false,"fontSize":14,"textHeight":14,"isBold":false,"isItalic":false},{"x":780,"y":280,"text":"классы\nуменьшаются\nв цикле -8 до\nконца поля ||\nпересечения","width":100,"height":80,"type":"Блок","isMenuBlock":false,"fontSize":14,"textHeight":14,"isBold":false,"isItalic":false},{"x":780,"y":100,"text":"вверх / вниз","width":80,"height":20,"type":"Текст","isMenuBlock":false,"fontSize":14,"textHeight":14,"isBold":false,"isItalic":false},{"x":780,"y":180,"text":"нажата\nстрелка вверх","width":100,"height":40,"type":"Блок","isMenuBlock":false,"fontSize":14,"textHeight":14,"isBold":false,"isItalic":false},{"x":780,"y":420,"text":"нажата\nстрелка вниз","width":100,"height":60,"type":"Блок","isMenuBlock":false,"fontSize":14,"textHeight":14,"isBold":false,"isItalic":false},{"x":1060,"y":100,"text":"вправо / влево","width":100,"height":20,"type":"Текст","isMenuBlock":false,"fontSize":14,"textHeight":14,"isBold":false,"isItalic":false},{"x":1060,"y":180,"text":"нажата\nстрелка вправо","width":100,"height":40,"type":"Блок","isMenuBlock":false,"fontSize":14,"textHeight":14,"isBold":false,"isItalic":false},{"x":1060,"y":300,"text":"классы\nприбавляются\nв цикле +1 до\nконца поля ||\nпересечения","width":100,"height":80,"type":"Блок","isMenuBlock":false,"fontSize":14,"textHeight":14,"isBold":false,"isItalic":false},{"x":1060,"y":420,"text":"\nнажата\nстрелка влево\n","width":100,"height":60,"type":"Блок","isMenuBlock":false,"fontSize":14,"textHeight":14,"isBold":false,"isItalic":false},{"x":1060,"y":530,"text":"классы\nуменьшаются\nв цикле -1 до\nконца поля ||\nпересечения","width":100,"height":80,"type":"Блок","isMenuBlock":false,"fontSize":14,"textHeight":14,"isBold":false,"isItalic":false},{"x":920,"y":40,"text":"конец поля можно определить\nпроверкой наличия i-того класса в массиве с крайними классами","width":430,"height":40,"type":"Текст","isMenuBlock":false,"fontSize":14,"textHeight":14,"isBold":false,"isItalic":false},{"x":510,"y":730,"text":"игроки\nили\nкомпьютер\n= пустое можество\n","width":240,"height":120,"type":"Условие","isMenuBlock":false,"fontSize":14,"textHeight":14,"isBold":false,"isItalic":false,"labelsPosition":1},{"x":770,"y":730,"text":"конец игры","width":100,"height":40,"type":"Блок","isMenuBlock":false,"fontSize":14,"textHeight":14,"isBold":false,"isItalic":false}],"arrows":[{"startIndex":2,"endIndex":3,"startConnectorIndex":2,"endConnectorIndex":0,"nodes":[{"x":510,"y":200},{"x":510,"y":210},{"x":510,"y":230}],"counts":[1,1,1]},{"startIndex":3,"endIndex":1,"startConnectorIndex":2,"endConnectorIndex":0,"nodes":[{"x":510,"y":290},{"x":510,"y":320},{"x":510,"y":340}],"counts":[1,1,1]},{"startIndex":1,"endIndex":0,"startConnectorIndex":2,"endConnectorIndex":0,"nodes":[{"x":510,"y":400},{"x":510,"y":420},{"x":510,"y":440}],"counts":[1,1,1]},{"startIndex":0,"endIndex":4,"startConnectorIndex":2,"endConnectorIndex":0,"nodes":[{"x":510,"y":480},{"x":510,"y":520},{"x":510,"y":540}],"counts":[1,1,1]},{"startIndex":8,"endIndex":6,"startConnectorIndex":2,"endConnectorIndex":0,"nodes":[{"x":780,"y":200},{"x":780,"y":220},{"x":780,"y":240}],"counts":[1,1,1]},{"startIndex":9,"endIndex":5,"startConnectorIndex":2,"endConnectorIndex":0,"nodes":[{"x":780,"y":450},{"x":780,"y":470},{"x":780,"y":490}],"counts":[1,1,1]},{"startIndex":11,"endIndex":12,"startConnectorIndex":2,"endConnectorIndex":0,"nodes":[{"x":1060,"y":200},{"x":1060,"y":240},{"x":1060,"y":260}],"counts":[1,1,1]},{"startIndex":13,"endIndex":14,"startConnectorIndex":2,"endConnectorIndex":0,"nodes":[{"x":1060,"y":450},{"x":1060,"y":470},{"x":1060,"y":490}],"counts":[1,1,1]},{"startIndex":16,"endIndex":1,"startConnectorIndex":3,"endConnectorIndex":3,"nodes":[{"x":390,"y":730},{"x":370,"y":730},{"x":370,"y":370},{"x":440,"y":370},{"x":460,"y":370}],"counts":[1,1,1,1,1]},{"startIndex":16,"endIndex":17,"startConnectorIndex":1,"endConnectorIndex":3,"nodes":[{"x":630,"y":730},{"x":700,"y":730},{"x":720,"y":730}],"counts":[1,1,1]}],"x0":0,"y0":0}